pindakaas-0.2.2.dist-info/METADATA
pindakaas-0.2.2.dist-info/WHEEL
pindakaas/__init__.py
pindakaas/encoding.py
pindakaas/pindakaas.cpython-38-i386-linux-gnu.so
pindakaas/solver.py
pindakaas-0.2.2.dist-info/RECORD
