Metadata-Version: 2.4
Name: pindakaas
Version: 0.2.2
Classifier: Development Status :: 4 - Beta
Classifier: Programming Language :: Rust
Classifier: Topic :: Scientific/Engineering :: Artificial Intelligence
Classifier: Topic :: Scientific/Engineering :: Mathematics
Classifier: Programming Language :: Python :: Implementation :: CPython
Classifier: Programming Language :: Python :: Implementation :: PyPy
Classifier: Programming Language :: Python :: 3
Classifier: Programming Language :: Python :: 3.8
Classifier: Programming Language :: Python :: 3.9
Classifier: Programming Language :: Python :: 3.10
Classifier: Programming Language :: Python :: 3.11
Classifier: Programming Language :: Python :: 3.12
Summary: Boolean satisfiability (SAT) library with efficient encoding of complex constraints and solver interaction
Keywords: satisfiability,encoding,boolean,logic,sat
Home-Page: https://github.com/pindakaashq/pindakaas
Author-email: "Jip J. Dekker" <jip@dekker.one>, Hendrik 'Henk' Bierlee <henk.bierlee@kuleuven.be>
License-Expression: MPL-2.0
Requires-Python: >=3.8
Project-URL: documentation, https://pindakaas.readthedocs.io/en/latest/
Project-URL: repository, https://github.com/pindakaashq/pindakaas.git
Project-URL: issues, https://github.com/pindakaashq/pindakaas/issues
Project-URL: changelog, https://github.com/pindakaashq/pindakaas/blob/develop/crates/pyndakaas/CHANGELOG.md
